agentify_sdk-1.0.0.dist-info/licenses/LICENSE.md
core/__init__.py
core/agent_standard/AGENT_ANATOMY.md
core/agent_standard/QUICKSTART.md
core/agent_standard/QUICKSTART_COMPLETE.md
core/agent_standard/README.md
core/agent_standard/__init__.py
core/agent_standard/cli/__init__.py
core/agent_standard/cli/main.py
core/agent_standard/core/__init__.py
core/agent_standard/core/agent.py
core/agent_standard/core/desire_monitor.py
core/agent_standard/core/ethics_engine.py
core/agent_standard/core/oversight.py
core/agent_standard/core/runtime.py
core/agent_standard/decorators/__init__.py
core/agent_standard/decorators/class_decorator.py
core/agent_standard/decorators/tool_decorator.py
core/agent_standard/decorators/wrapper.py
core/agent_standard/examples/complete_agent_example.json
core/agent_standard/examples/desktop_automation_agent.json
core/agent_standard/examples/meeting_assistant.json
core/agent_standard/models/__init__.py
core/agent_standard/models/authority.py
core/agent_standard/models/desires.py
core/agent_standard/models/ethics.py
core/agent_standard/models/io_contracts.py
core/agent_standard/models/manifest.py
core/agent_standard/prompts/README.md
core/agent_standard/prompts/create_agent.md
core/agent_standard/prompts/wrap_existing_code.md
core/agent_standard/templates/README.md
core/agent_standard/templates/agent_manifest_template.json
core/agent_standard/templates/minimal_agent_template.json
core/agent_standard/validation/__init__.py
core/agent_standard/validation/authority_validator.py
core/agent_standard/validation/compliance_checker.py
core/agent_standard/validation/manifest_validator.py
agentify_sdk-1.0.0.dist-info/METADATA
agentify_sdk-1.0.0.dist-info/WHEEL
agentify_sdk-1.0.0.dist-info/entry_points.txt
agentify_sdk-1.0.0.dist-info/top_level.txt
agentify_sdk-1.0.0.dist-info/RECORD
